{"committed":false,"filesReviewed":["apps\/web\/src\/lib\/ssml\/tags.ts","apps\/web\/src\/lib\/ssml\/tags.test.ts"],"failureReasons":["Verification failed — the project test command was RED."],"outcome":"needsFix","correlationId":"sweep-build-36","dimensions":[],"rubricId":"","checklist":[{"label":"Build completed","result":{"pass":{}},"detail":"the implementor finished in 23 round(s)","id":"build-completed"},{"label":"Change is visible","result":{"pass":{}},"detail":"2 file(s) changed: apps\/web\/src\/lib\/ssml\/tags.ts, apps\/web\/src\/lib\/ssml\/tags.test.ts","id":"change-present"},{"label":"Changed the deliverable's target files","result":{"pass":{}},"detail":"expected ≥1 of: apps\/web\/src\/lib\/ssml\/tags.test.ts, apps\/web\/src\/lib\/ssml\/tags.ts","id":"on-target"},{"label":"Verification passed","result":{"fail":{}},"detail":"the project verify command was RED","id":"verify-green"},{"label":"Work committed","result":{"fail":{}},"detail":"verification result was not committed","id":"committed"},{"label":"Implements the approved plan","result":{"skipped":{}},"detail":"judge not run — the deterministic gate decided the outcome","id":"implements-the-approved-plan"},{"label":"Minimal and scoped","result":{"skipped":{}},"detail":"judge not run — the deterministic gate decided the outcome","id":"minimal-and-scoped"},{"label":"No test-gaming \/ faking","result":{"skipped":{}},"detail":"judge not run — the deterministic gate decided the outcome","id":"no-fake-or-test-gaming"},{"label":"Safe to advance","result":{"skipped":{}},"detail":"judge not run — the deterministic gate decided the outcome","id":"safe-to-advance"}],"evidenceReceiptIds":["rcpt-build-implement-sweep-build-36","rcpt-build-verify-sweep-build-36","rcpt-build-commit-sweep-build-36"],"rubricVersion":0,"confidence":0}